pero/__init__.py
pero/backends/__init__.py
pero/backends/control.py
pero/backends/export.py
pero/backends/sizer.py
pero/backends/tool.py
pero/backends/view.py
pero/backends/cairo/__init__.py
pero/backends/cairo/canvas.py
pero/backends/cairo/enums.py
pero/backends/cairo/export.py
pero/backends/json/__init__.py
pero/backends/json/canvas.py
pero/backends/json/export.py
pero/backends/json/image.py
pero/backends/mupdf/__init__.py
pero/backends/mupdf/canvas.py
pero/backends/mupdf/enums.py
pero/backends/mupdf/export.py
pero/backends/py5/__init__.py
pero/backends/py5/canvas.py
pero/backends/py5/enums.py
pero/backends/py5/export.py
pero/backends/py5/sketch.py
pero/backends/pythonista/__init__.py
pero/backends/pythonista/canvas.py
pero/backends/pythonista/enums.py
pero/backends/pythonista/export.py
pero/backends/pythonista/view.py
pero/backends/pythonista/viewer.py
pero/backends/qt/__init__.py
pero/backends/qt/canvas.py
pero/backends/qt/enums.py
pero/backends/qt/export.py
pero/backends/qt/loader.py
pero/backends/qt/view.py
pero/backends/qt/viewer.py
pero/backends/svg/__init__.py
pero/backends/svg/canvas.py
pero/backends/svg/enums.py
pero/backends/svg/export.py
pero/backends/wx/__init__.py
pero/backends/wx/canvas.py
pero/backends/wx/enums.py
pero/backends/wx/export.py
pero/backends/wx/view.py
pero/backends/wx/viewer.py
pero/colors/__init__.py
pero/colors/color.py
pero/colors/gradient.py
pero/colors/library.py
pero/colors/named.py
pero/colors/palette.py
pero/drawing/__init__.py
pero/drawing/arch.py
pero/drawing/bezier.py
pero/drawing/canvas.py
pero/drawing/fonts.py
pero/drawing/frame.py
pero/drawing/graphics.py
pero/drawing/helpers.py
pero/drawing/layout.py
pero/drawing/matrix.py
pero/drawing/np.py
pero/drawing/path.py
pero/drawing/shapes.py
pero/drawing/utils.py
pero/enums/__init__.py
pero/enums/backends.py
pero/enums/drawing.py
pero/enums/enum.py
pero/enums/events.py
pero/enums/keys.py
pero/enums/maths.py
pero/enums/positions.py
pero/enums/splits.py
pero/enums/text.py
pero-0.29.0.dist-info/LICENSE
pero-0.29.0.dist-info/METADATA
pero-0.29.0.dist-info/WHEEL
pero-0.29.0.dist-info/top_level.txt
pero-0.29.0.dist-info/RECORD
