Metadata-Version: 2.1
Name: pero
Version: 0.29.0
Summary: Draw consistently with various backends
Home-page: https://github.com/xxao/pero
Author: Martin Strohalm
Author-email: 
License: MIT
Classifier: Development Status :: 3 - Alpha
Classifier: Programming Language :: Python :: 3 :: Only
Classifier: Operating System :: OS Independent
Classifier: Topic :: Multimedia :: Graphics :: Presentation
Classifier: Topic :: Scientific/Engineering
Classifier: Intended Audience :: Developers
Classifier: Intended Audience :: Science/Research
License-File: LICENSE
Requires-Dist: numpy
Requires-Dist: Pillow
